Workbook

Sheet ReadMe & Rubric
B2: B2B Distribution — Function & Automation-Opportunity Map (post-LLM)
B3: Iksula | Vertical Process-Mapping Series — Template & reference file
B5: Vertical | C5: B2B Distribution (wholesalers / stockists / value-added distributors buying from principals and selling onward to retailers, resellers and businesses)
B6: Organization archetype | C6: Single distributor running its own P&L (own balance sheet; every inefficiency is its own cost, every recovered rupee is its own margin)
B7: Prepared by | C7: Process-mapping consultant (ecommerce + adjacent enterprise functions)
B8: Date | C8: 31 May 2026
B9: Eventual purpose | C9: Source-of-truth to design and build Iksula solutions; comparable across verticals via standard taxonomy + rubric
B10: Economic lens | C10: Thin-margin model: prize is LEAKAGE RECOVERY + WORKING-CAPITAL RELEASE, not headcount reduction
B12: How to read this workbook (tab guide)
B13: Coverage Map | C13: Every function in scope + completion status. The mandatory self-audit, made visible.
B14: Function Narratives | C14: Prose deep-dive per function: process spine, tools, obvious vs non-obvious plays.
B15: Task Matrix | C15: The engine. One row per L3 task, scored 1-5 with composite priority. Sort/filter to build a roadmap.
B16: Cross-Cutting Horizontals | C16: Build-once / sell-many layers + the 'recovery & leakage' theme that spans departments.
B17: Iksula Solution Shortlist | C17: Prioritised, sequenced opportunities with the productizable / reuse angle made explicit.
B19: Scoring rubric (all 1-5; higher = better / more feasible)
B20: Impact | C20: Value created if solved. 1 = marginal; 3 = meaningful efficiency; 5 = transformative margin / working-capital / risk impact.
B21: Data Readiness | C21: 1 = data scattered, dirty or unavailable; 5 = clean, structured, accessible data already exists.
B22: Integration Ease | C22: 1 = deep multi-system / core-ERP integration required; 5 = standalone or light-touch integration.
B23: Accuracy Tolerance | C23: How forgiving the task is of model error. 1 = zero tolerance (financial / statutory / compliance); 5 = high tolerance (drafts, suggestions, human-reviewed).
B24: Feasibility (calc) | C24: AVERAGE of Data Readiness, Integration Ease and Accuracy Tolerance. Auto-computed.
B25: Composite Priority (calc) | C25: Average of Impact and Feasibility (1-5 scale). Auto-computed. Sort descending to prioritise.
B26: Priority Tier (calc) | C26: P1 if Composite >= 3.8; P2 if >= 3.0; else P3.
B27: Quick Win (calc) | C27: Yes if Impact >= 4 AND Feasibility >= 3.5 (high value, low friction).
B29: Controlled vocabularies (keep identical across verticals for comparability)
B30: Solution Archetype | C30: Doc-Extraction Pipeline | Copilot / Agent-Assist | Autonomous Agent | NL-Analytics | RPA+LLM Hybrid | Semantic Search | Predictive Model
B31: Value Lever | C31: Leakage Recovery | Working Capital | Cost-to-Serve | Revenue Growth | Risk / Compliance
B32: Reusability | C32: High = reusable across most verticals as-is | Med = reusable with config | Low = vertical/client-specific
B33: Productizable | C33: Productizable = repeatable product/offering | Hybrid = product core + bespoke config | Bespoke = client-specific build
B34: Driver Metric | C34: What the value scales with (e.g., # principals x scheme volume) — used to size the prize per client.

Sheet Coverage Map
A1: Group | B1: Function | C1: Status | D1: # L3 Tasks Mapped | E1: Notes
A2: Commercial / Revenue | B2: Field Sales | C2: Done | D2: =COUNTIF('Task Matrix'!B:B,B2) -> 6 | E2: Beat sales; order booking, market intel, door collections
A3: Commercial / Revenue | B3: Inside Sales / Telesales | C3: Done | D3: =COUNTIF('Task Matrix'!B:B,B3) -> 4 | E3: Remote order-taking, reorder, upsell
A4: Commercial / Revenue | B4: Key Account Management | C4: Done | D4: =COUNTIF('Task Matrix'!B:B,B4) -> 4 | E4: Large / EDI-integrated customers, JBPs, QBRs
A5: Commercial / Revenue | B5: Sales Operations | C5: Done | D5: =COUNTIF('Task Matrix'!B:B,B5) -> 4 | E5: Targets, incentives, beat design, sales analytics
A6: Commercial / Revenue | B6: Marketing / Trade Marketing | C6: Done | D6: =COUNTIF('Task Matrix'!B:B,B6) -> 4 | E6: Trade schemes comms, co-marketing (MDF), campaigns
A7: Commercial / Revenue | B7: Category & Assortment | C7: Done | D7: =COUNTIF('Task Matrix'!B:B,B7) -> 4 | E7: Range planning, principal management, NPD
A8: Commercial / Revenue | B8: Pricing & Margin Mgmt | C8: Done | D8: =COUNTIF('Task Matrix'!B:B,B8) -> 3 | E8: List / tier pricing, deal desk, margin monitoring
A9: Commercial / Revenue | B9: B2B Ecommerce Channel | C9: Done | D9: =COUNTIF('Task Matrix'!B:B,B9) -> 4 | E9: Portal merchandising, search, adoption, digital ops
A10: Commercial / Revenue | B10: Customer Service / Order Mgmt | C10: Done | D10: =COUNTIF('Task Matrix'!B:B,B10) -> 7 | E10: Status, complaints, returns, inquiries
A11: Supply Chain / Ops | B11: Procurement / Purchasing (P2P) | C11: Done | D11: =COUNTIF('Task Matrix'!B:B,B11) -> 4 | E11: Buying, PO, GRN, 3-way match
A12: Supply Chain / Ops | B12: Demand & Inventory Planning | C12: Done | D12: =COUNTIF('Task Matrix'!B:B,B12) -> 5 | E12: Forecast, replenish, near-expiry / dead stock
A13: Supply Chain / Ops | B13: Warehouse / DC Operations | C13: Done | D13: =COUNTIF('Task Matrix'!B:B,B13) -> 4 | E13: Inbound, putaway, pick, pack, dispatch
... A29: Enabling / Support | B29: Admin / Facilities | C29: Done | D29: =COUNTIF('Task Matrix'!B:B,B29) -> 3 | E29: Vendor / AMC, document management
B30: TOTAL L3 TASKS MAPPED | D30: =SUM(D2:D29) -> 117

Sheet Function Narratives
A1: Group | B1: Function | C1: Process Spine (L1 -> L2 -> L3 hotspots) | D1: Typical Tools | E1: Obvious Automation | F1: Non-Obvious, High-Value Plays
A2: Commercial / Revenue | B2: Field Sales | C2: Beat/route planning -> outlet visits -> order booking -> in-store merchandising -> market intel -> door collections. Hotspots: territory design, order keying, lost market feedback. | D2: SFA/DMS (Bizom, FieldAssist), mobile order app | E2: Auto attendance/geo-tracking; standard visit reports. | F2: Voice-to-order dictation structured by LLM; suggested-order per outlet (assortment-gap + cycle); mining free-text visit notes into structured competitor/stock-out/new-outlet intel; new-outlet onboarding from shop photo + GST; rep coaching summaries flagging declining outlets.
A3: Commercial / Revenue | B3: Inside Sales / Telesales | C3: Call list -> reorder prompts -> upsell -> order entry. Hotspots: prep, prioritisation, on-call recall, logging. | D3: CRM, ERP, dialer | E3: Auto-dial lists; order entry assist. | F3: Per-account call-prep brief (buys / overdue / scheme / lapsed lines); reorder-due & churn prediction to sequence the list; real-time on-call cross-sell + scheme prompts; auto call summary into CRM.
A4: Commercial / Revenue | B4: Key Account Management | C4: Account/JBP planning -> EDI order handling -> fill-rate/SLA mgmt -> QBRs. Hotspots: review prep, compliance tracking, tenders. | D4: ERP, EDI, Excel/PPT | E4: EDI order automation; standard dashboards. | F4: Auto-generated QBR decks from sales/service/fill-rate data; SLA-and-pricing compliance monitoring vs signed terms; RFQ/tender response drafting for institutional buyers.
A5: Commercial / Revenue | B5: Sales Operations | C5: Targets -> beat design -> incentive computation -> analytics -> trade-spend. Hotspots: payout calc, dispute, ad-hoc analysis. | D5: ERP, Excel, BI | E5: Target dashboards; payout templates. | F5: Incentive/commission computation from complex multi-scheme rules + dispute resolution; natural-language analytics ('why did East drop 8%?'); auto sales-review commentary; beat-redesign recommendations.
A6: Commercial / Revenue | B6: Marketing / Trade Marketing | C6: Trade-scheme comms -> principal co-marketing -> portal/WhatsApp campaigns -> performance. Hotspots: collateral, MDF claims. | D6: Canva, CMS, BI | E6: Localised content generation; campaign reporting. | F6: MDF / co-marketing claim documentation (leakage-prone, same pattern as schemes); scale generation of retailer collateral; localised multilingual campaign content.
A7: Commercial / Revenue | B7: Category & Assortment | C7: Range planning -> principal/brand mgmt -> listing decisions -> NPD. Hotspots: gap analysis, add/drop, scorecards. | D7: ERP, BI, Excel | E7: Principal performance scorecards; listing reports. | F7: Assortment-gap & range-rationalisation analysis by outlet class; cannibalisation/substitute reasoning; NPD launch-plan drafting.
A8: Commercial / Revenue | B8: Pricing & Margin Mgmt | C8: List price -> tier/customer pricing -> deal desk -> margin monitoring. Hotspots: leakage, price propagation, deal evaluation. | D8: ERP, Excel | E8: Price list uploads. | F8: Margin-leakage detection (below-floor sales; landed cost rose but price didn't); auto price-change propagation from principal price lists; deal-desk copilot scoring requests vs floors + precedent.
A9: Commercial / Revenue | B9: B2B Ecommerce Channel | C9: Portal merchandising -> search -> promotions -> adoption -> digital order ops. Hotspots: search, personalisation, channel shift. | D9: B2B portal/CMS | E9: FAQ deflection; promo banners. | F9: Semantic search over large poorly-tagged catalog; per-buyer personalised assortment; channel-shift campaigns nudging offline buyers onto the portal; auto-merchandising of scheme/near-expiry/slow SKUs.
A10: Commercial / Revenue | B10: Customer Service / Order Mgmt | C10: Order status -> complaints -> returns -> inquiries -> routing. Hotspots: status volume, discrepancy calls, photo complaints, VOC. | D10: Helpdesk (Freshdesk, Zoho), WhatsApp, ERP | E10: Status chatbot; FAQ deflection. | F10: 'Why is my order short?' auto-explainer (stockout/credit hold/MOQ); complaint intake from photos -> auto CN/replacement; VOC mining for systemic batch/route issues; proactive delay/partial alerts; returns-eligibility check; agent-assist drafting.
A11: Supply Chain / Ops | B11: Procurement / Purchasing (P2P) | C11: Demand signal -> PO -> principal coord -> GRN -> invoice match -> pay. Hotspots: PO sizing, scheme timing, 3-way match. | D11: ERP | E11: Auto-PO from reorder points. | F11: Scheme-timed buying (buy more when a principal scheme is live -> feeds claims); 3-way match across format mismatches; auto-drafted principal correspondence (shortages, expiry/return).
A12: Supply Chain / Ops | B12: Demand & Inventory Planning | C12: Forecast -> replenish -> allocate -> slow/dead/near-expiry. Hotspots: forecast accuracy, expiry, balancing. | D12: Planning tool, Excel, ERP | E12: Statistical forecasting; reorder alerts. | F12: Near-expiry liquidation targeting (avoids write-off/return); forecast enrichment with festival/weather/event context; analog-SKU forecasting for new products; inter-branch stock-balancing; exception narration.
... A29: Enabling / Support | B29: Admin / Facilities | C29: Vendor/AMC mgmt -> document mgmt -> travel. Hotspots: invoices, renewals, retrieval. | D29: Excel, file shares | E29: Travel booking tools. | F29: AMC/vendor invoice processing; contract-renewal tracking; semantic document search/retrieval.

Sheet Task Matrix
A1: Group | B1: Function | C1: L1 Sub-process | D1: L2 Process | E1: L3 Task | F1: Current Tools | G1: Manual Hotspot / Pain | H1: AI / Automation Opportunity | I1: Obvious / Non-obvious | J1: Solution Archetype | K1: Value Lever | L1: Driver Metric (scales with) | M1: Impact | N1: Data Readiness | O1: Integration Ease | P1: Accuracy Tolerance | Q1: Feasibility | R1: Composite Priority | S1: Priority Tier | T1: Quick Win | U1: Reusability | V1: Productizable | W1: Economic Buyer
A2: Commercial / Revenue | B2: Field Sales | C2: Beat & Coverage | D2: Beat planning | E2: Design optimal beat/route per rep | F2: SFA/DMS | G2: Manual territory design, uneven coverage | H2: Route/beat optimisation recommendations | I2: Non-obvious | J2: Predictive Model | K2: Cost-to-Serve | L2: # outlets x reps | M2: 4 | N2: 3 | O2: 3 | P2: 4 | Q2: =ROUND(AVERAGE(N2:P2),1) -> 3.3 | R2: =ROUND((M2+Q2)/2,1) -> 3.7 | S2: =IF(R2>=3.8,"P1",IF(R2>=3,"P2","P3")) -> P2 | T2: =IF(AND(M2>=4,Q2>=3.5),"Yes","No") -> No | U2: Med | V2: Hybrid | W2: Head of Sales
A3: Commercial / Revenue | B3: Field Sales | C3: Order Booking | D3: Order capture | E3: Generate suggested order per outlet | F3: SFA/DMS | G3: Rep guesses upsell; assortment gaps missed | H3: Next-best-order from purchase history + gaps | I3: Non-obvious | J3: Predictive Model | K3: Revenue Growth | L3: # outlets x SKUs | M3: 5 | N3: 4 | O3: 3 | P3: 4 | Q3: =ROUND(AVERAGE(N3:P3),1) -> 3.7 | R3: =ROUND((M3+Q3)/2,1) -> 4.4 | S3: =IF(R3>=3.8,"P1",IF(R3>=3,"P2","P3")) -> P1 | T3: =IF(AND(M3>=4,Q3>=3.5),"Yes","No") -> Yes | U3: High | V3: Productizable | W3: Head of Sales
A4: Commercial / Revenue | B4: Field Sales | C4: Order Booking | D4: Order capture | E4: Capture order via voice/photo at outlet | F4: SFA/WhatsApp | G4: Manual keying, errors | H4: Voice/image-to-structured-order + SKU match | I4: Non-obvious | J4: Doc-Extraction Pipeline | K4: Cost-to-Serve | L4: order volume | M4: 4 | N4: 3 | O4: 3 | P4: 3 | Q4: =ROUND(AVERAGE(N4:P4),1) -> 3 | R4: =ROUND((M4+Q4)/2,1) -> 3.5 | S4: =IF(R4>=3.8,"P1",IF(R4>=3,"P2","P3")) -> P2 | T4: =IF(AND(M4>=4,Q4>=3.5),"Yes","No") -> No | U4: High | V4: Productizable | W4: Head of Sales
A5: Commercial / Revenue | B5: Field Sales | C5: Market Intel | D5: Field feedback | E5: Log market & competitor intel from visit | F5: SFA notes | G5: Free-text feedback lost / unused | H5: Mine visit notes into structured intel | I5: Non-obvious | J5: NL-Analytics | K5: Revenue Growth | L5: # visits | M5: 3 | N5: 3 | O5: 4 | P5: 4 | Q5: =ROUND(AVERAGE(N5:P5),1) -> 3.7 | R5: =ROUND((M5+Q5)/2,1) -> 3.4 | S5: =IF(R5>=3.8,"P1",IF(R5>=3,"P2","P3")) -> P2 | T5: =IF(AND(M5>=4,Q5>=3.5),"Yes","No") -> No | U5: High | V5: Productizable | W5: Head of Sales
A6: Commercial / Revenue | B6: Field Sales | C6: Onboarding | D6: New outlet | E6: Onboard new outlet from shop photo + GST | F6: SFA/manual | G6: Slow KYC & master setup | H6: Auto-draft customer master from photo + GST | I6: Non-obvious | J6: Doc-Extraction Pipeline | K6: Cost-to-Serve | L6: # new outlets | M6: 3 | N6: 3 | O6: 3 | P6: 3 | Q6: =ROUND(AVERAGE(N6:P6),1) -> 3 | R6: =ROUND((M6+Q6)/2,1) -> 3 | S6: =IF(R6>=3.8,"P1",IF(R6>=3,"P2","P3")) -> P2 | T6: =IF(AND(M6>=4,Q6>=3.5),"Yes","No") -> No | U6: High | V6: Productizable | W6: Head of Sales
A7: Commercial / Revenue | B7: Field Sales | C7: People | D7: Coaching | E7: Generate rep performance coaching summary | F7: Dashboards | G7: Manual, infrequent reviews | H7: Auto coaching summaries + declining-outlet flags | I7: Non-obvious | J7: NL-Analytics | K7: Revenue Growth | L7: # reps | M7: 3 | N7: 4 | O7: 4 | P7: 4 | Q7: =ROUND(AVERAGE(N7:P7),1) -> 4 | R7: =ROUND((M7+Q7)/2,1) -> 3.5 | S7: =IF(R7>=3.8,"P1",IF(R7>=3,"P2","P3")) -> P2 | T7: =IF(AND(M7>=4,Q7>=3.5),"Yes","No") -> No | U7: High | V7: Productizable | W7: Head of Sales
A8: Commercial / Revenue | B8: Inside Sales / Telesales | C8: Telecalling | D8: Call prep | E8: Build per-account call brief | F8: CRM/ERP | G8: Manual lookup before each call | H8: Auto per-account brief (buys/overdue/scheme) | I8: Non-obvious | J8: Copilot / Agent-Assist | K8: Revenue Growth | L8: # accounts | M8: 4 | N8: 4 | O8: 3 | P8: 4 | Q8: =ROUND(AVERAGE(N8:P8),1) -> 3.7 | R8: =ROUND((M8+Q8)/2,1) -> 3.9 | S8: =IF(R8>=3.8,"P1",IF(R8>=3,"P2","P3")) -> P1 | T8: =IF(AND(M8>=4,Q8>=3.5),"Yes","No") -> Yes | U8: High | V8: Productizable | W8: Head of Sales
A9: Commercial / Revenue | B9: Inside Sales / Telesales | C9: Telecalling | D9: Prioritisation | E9: Prioritise reorder-due accounts | F9: ERP | G9: Static / manual call lists | H9: Reorder & churn prediction to sequence list | I9: Non-obvious | J9: Predictive Model | K9: Revenue Growth | L9: # accounts x cycle | M9: 4 | N9: 4 | O9: 4 | P9: 4 | Q9: =ROUND(AVERAGE(N9:P9),1) -> 4 | R9: =ROUND((M9+Q9)/2,1) -> 4 | S9: =IF(R9>=3.8,"P1",IF(R9>=3,"P2","P3")) -> P1 | T9: =IF(AND(M9>=4,Q9>=3.5),"Yes","No") -> Yes | U9: High | V9: Productizable | W9: Head of Sales
A10: Commercial / Revenue | B10: Inside Sales / Telesales | C10: Telecalling | D10: On-call | E10: On-call cross-sell & scheme prompts | F10: None | G10: Reps forget cross-sell / schemes | H10: Real-time agent assist | I10: Non-obvious | J10: Copilot / Agent-Assist | K10: Revenue Growth | L10: call volume | M10: 3 | N10: 3 | O10: 2 | P10: 4 | Q10: =ROUND(AVERAGE(N10:P10),1) -> 3 | R10: =ROUND((M10+Q10)/2,1) -> 3 | S10: =IF(R10>=3.8,"P1",IF(R10>=3,"P2","P3")) -> P2 | T10: =IF(AND(M10>=4,Q10>=3.5),"Yes","No") -> No | U10: Med | V10: Hybrid | W10: Head of Sales
A11: Commercial / Revenue | B11: Inside Sales / Telesales | C11: Telecalling | D11: Logging | E11: Auto-summarise call into CRM | F11: CRM | G11: Logging skipped / thin | H11: Auto call summary to CRM | I11: Obvious | J11: Copilot / Agent-Assist | K11: Cost-to-Serve | L11: call volume | M11: 3 | N11: 4 | O11: 4 | P11: 5 | Q11: =ROUND(AVERAGE(N11:P11),1) -> 4.3 | R11: =ROUND((M11+Q11)/2,1) -> 3.7 | S11: =IF(R11>=3.8,"P1",IF(R11>=3,"P2","P3")) -> P2 | T11: =IF(AND(M11>=4,Q11>=3.5),"Yes","No") -> No | U11: High | V11: Productizable | W11: Head of Sales
A12: Commercial / Revenue | B12: Key Account Management | C12: Account Mgmt | D12: Reviews | E12: Generate QBR deck from data | F12: Excel/PPT | G12: Hours of manual prep | H12: Auto QBR deck from sales/service data | I12: Non-obvious | J12: NL-Analytics | K12: Revenue Growth | L12: # key accounts | M12: 4 | N12: 4 | O12: 3 | P12: 4 | Q12: =ROUND(AVERAGE(N12:P12),1) -> 3.7 | R12: =ROUND((M12+Q12)/2,1) -> 3.9 | S12: =IF(R12>=3.8,"P1",IF(R12>=3,"P2","P3")) -> P1 | T12: =IF(AND(M12>=4,Q12>=3.5),"Yes","No") -> Yes | U12: High | V12: Productizable | W12: Head of Sales
A13: Commercial / Revenue | B13: Key Account Management | C13: Account Mgmt | D13: Compliance | E13: Monitor SLA/fill-rate/pricing vs contract | F13: ERP | G13: Manual / no tracking | H13: Auto breach detection vs signed terms | I13: Non-obvious | J13: Copilot / Agent-Assist | K13: Risk / Compliance | L13: # contracts | M13: 4 | N13: 3 | O13: 3 | P13: 3 | Q13: =ROUND(AVERAGE(N13:P13),1) -> 3 | R13: =ROUND((M13+Q13)/2,1) -> 3.5 | S13: =IF(R13>=3.8,"P1",IF(R13>=3,"P2","P3")) -> P2 | T13: =IF(AND(M13>=4,Q13>=3.5),"Yes","No") -> No | U13: Med | V13: Hybrid | W13: Head of Sales
... A118: Enabling / Support | B118: Admin / Facilities | C118: Documents | D118: Retrieval | E118: Document search / retrieval | F118: File shares | G118: Slow retrieval | H118: Semantic document search | I118: Obvious | J118: Semantic Search | K118: Cost-to-Serve | L118: doc volume | M118: 2 | N118: 3 | O118: 4 | P118: 4 | Q118: =ROUND(AVERAGE(N118:P118),1) -> 3.7 | R118: =ROUND((M118+Q118)/2,1) -> 2.9 | S118: =IF(R118>=3.8,"P1",IF(R118>=3,"P2","P3")) -> P3 | T118: =IF(AND(M118>=4,Q118>=3.5),"Yes","No") -> No | U118: High | V118: Productizable | W118: COO

Sheet Cross-Cutting Horizontals
A1: Cross-Cutting Horizontals & Themes — build once, deploy many
A2: A full-company sweep reveals that most non-obvious wins reduce to a few shared capabilities + one cross-departmental theme. Building these as platforms (not per-department point tools) is the difference between 30 pilots and a compounding capability.
A4: Theme / Horizontal | B4: What it is | C4: Functions it spans | D4: Why build once | E4: Solution Archetype | F4: Reuse value for Iksula
A5: 1. Unstructured Document Understanding | B5: One extract-validate-structure engine for any inbound document, with confidence scoring + human-in-loop review. | C5: Order capture; cash application; deduction triage; scheme circulars; principal price lists; vendor/principal ledgers; bank statements; GRN; POD; freight bills; CoA; AP invoices; complaint photos; contracts. | D5: The same pipeline (ingest -> classify -> extract -> validate -> post) recurs everywhere; only the schema and target system change. Build the core once, add document templates per use case. | E5: Doc-Extraction Pipeline | F5: Very High — the backbone product. Most leakage-recovery and cost-to-serve wins sit on it; reusable across every vertical with new templates.
A6: 2. Natural-Language Analytics | B6: A semantic layer over the warehouse so any user asks 'why did X' and gets a sourced, narrated answer. | C6: Sales Ops; FP&A; Data/BI; GL variance; VOC mining; IT reporting; category analysis. | D6: One trusted semantic model + guardrails serves every department's ad-hoc and narrative analytics, removing the analyst bottleneck firm-wide. | E6: NL-Analytics | F6: High — horizontal product; per-client it needs only the data model mapped. Strong cross-vertical reuse.
A7: 3. Master-Data Spine | B7: Clean, deduped, classified item/customer/price/vendor master with live anomaly governance. | C7: Catalog/MDM; Pricing; Procurement; Planning; O2C; Ecommerce; Tax (HSN). | D7: Almost every other automation fails on dirty master data. Fixing the spine is the prerequisite that makes the rest reliable. | E7: Doc-Extraction + Semantic Search | F7: High — distribution-grade MDM is a repeatable offering; HSN/UOM logic reusable across India verticals.
A8: 4. Recovery & Leakage Cell (THEME) | B8: A single owner + tooling for every form of money owed-but-unclaimed or over-paid. | C8: Scheme claims; MDF/co-marketing claims; return-to-principal credits; freight overcharge; bank-charge audit; ITC recovery; early-pay discounts; margin leakage; AR deductions. | D8: For a thin-margin distributor this is the single highest-value theme, yet it is scattered across 6 departments with no owner. Consolidating it (org + tooling) turns scattered leaks into recovered margin. | E8: Doc-Extraction + NL-Analytics | F8: Very High — a flagship 'Recovery-as-a-Service' offering; outcome-based pricing possible (share of recovered value).
A9: 5. Conversational / Agent Interface | B9: A shared WhatsApp/portal assistant layer fronting ERP + knowledge for self-service. | C9: Order capture; Customer Service; IT helpdesk; HR queries; warehouse SOP. | D9: One conversational + retrieval layer, many skills. Build the channel + retrieval once, plug in domain skills. | E9: Autonomous Agent | F9: High — channel infrastructure reusable across functions and verticals; differentiator is the ERP/data grounding.

Sheet Iksula Solution Shortlist
A1: Iksula Solution Shortlist & Roadmap — B2B Distribution
A2: Sequenced by ROI-to-effort. Phase 1 = recover cash & margin (fast, high-certainty); Phase 2 = cut cost-to-serve & lift revenue; Phase 3 = scale the shared horizontals. Composite shown is the indicative average of the underlying Task-Matrix rows.
A4: # | B4: Solution | C4: What it does | D4: Functions served | E4: Primary Value Lever | F4: Economic Buyer | G4: Archetype | H4: Indic. Composite | I4: Reuse | J4: Productizable | K4: Phase | L4: Iksula rationale / GTM angle
A5: 1 | B5: Scheme Claim-Leakage Engine | C5: Parse principal scheme circulars to structured config; auto-compute eligibility; detect unclaimed schemes; reconcile filed vs settled and chase shortfalls. | D5: Recon & Claims; Procurement; Pricing | E5: Leakage Recovery | F5: CFO / Finance | G5: Doc-Extraction + NL-Analytics | H5: 4.2 | I5: High | J5: Productizable | K5: Phase 1 | L5: Flagship recovery product; outcome-based pricing (share of recovered claims) lands fast with the CFO.
A6: 2 | B6: Intelligent Cash Application + Deduction Triage | C6: Parse bank statements + remittance advice; auto-allocate lump-sum receipts across invoices; classify and route short-payments with proof. | D6: Order-to-Cash | E6: Working Capital | F6: CFO / Finance | G6: Doc-Extraction Pipeline | H6: 4.0 | I6: High | J6: Productizable | K6: Phase 1 | L6: Releases working capital and cuts DSO; tangible CFO metric; reusable across verticals.
A7: 3 | B7: Principal Price-List & Circular Ingestion | C7: Parse any-format principal price lists and circulars into item + price master updates; propagate price changes automatically. | D7: MDM; Pricing; Category | E7: Leakage Recovery | F7: CFO / Finance | G7: Doc-Extraction Pipeline | H7: 3.8 | I7: High | J7: Productizable | K7: Phase 1 | L7: Kills a huge recurring manual load and pricing errors; feeds claims & MDM spine.
A8: 4 | B8: Margin-Leakage Detector | C8: Flag below-floor sales, customers/SKUs where landed cost rose but price didn't, and dilutive accounts. | D8: Pricing; FP&A | E8: Leakage Recovery | F8: CFO / Finance | G8: NL-Analytics | H8: 3.6 | I8: High | J8: Productizable | K8: Phase 1 | L8: Direct margin recovery with light integration; quick proof-of-value.
A9: 5 | B9: Recovery Suite (Freight / Bank-charge / ITC / RTP) | C9: Audit transporter & bank charges vs contract; GSTR-2B vs purchase ITC matching + vendor chase; compile return-to-principal claims. | D9: Logistics; Treasury; Tax; Returns | E9: Leakage Recovery | F9: CFO / Finance | G9: Doc-Extraction Pipeline | H9: 3.7 | I9: High | J9: Productizable | K9: Phase 1 | L9: Bundles the scattered leakage points into one 'Recovery-as-a-Service' line; high cross-vertical reuse.
A10: 6 | B10: Unstructured Order Capture | C10: Convert WhatsApp/email/PDF/handwritten orders into structured, SKU-matched order lines. | D10: O2C; Field Sales; Inside Sales | E10: Cost-to-Serve | F10: COO / Operations | G10: Doc-Extraction Pipeline | H10: 3.7 | I10: High | J10: Productizable | K10: Phase 2 | L10: Collapses order-entry effort and error-driven returns; visible to commercial + ops.
A11: 7 | B11: Customer-Service Deflection Suite | C11: Order-status bot, 'why is my order short' explainer, complaint-from-photo intake, proactive delay alerts, VOC mining. | D11: Customer Service | E11: Cost-to-Serve | F11: COO / Operations | G11: Autonomous Agent | H11: 3.8 | I11: High | J11: Productizable | K11: Phase 2 | L11: Cuts ticket volume and surfaces systemic issues; clean SaaS-style offering.
A12: 8 | B12: Next-Best-Order + Channel-Shift | C12: Suggested order per outlet from history + gaps; detect offline buyers and nudge them onto the portal. | D12: Field/Inside Sales; Ecommerce | E12: Revenue Growth | F12: CRO/CMO / Commercial | G12: Predictive Model | H12: 3.9 | I12: High | J12: Productizable | K12: Phase 2 | L12: Lifts basket and shifts cost-to-serve down; ties to portal adoption KPIs.
A13: 9 | B13: Semantic Catalog Search + Substitutes | C13: Semantic search over the large catalog; auto-suggest alternates for out-of-stock SKUs. | D13: Ecommerce; MDM | E13: Revenue Growth | F13: CRO/CMO / Commercial | G13: Semantic Search | H13: 3.7 | I13: High | J13: Productizable | K13: Phase 2 | L13: Recovers lost portal orders; reusable catalog capability across verticals.
A14: 10 | B14: Company-wide NL Analytics Layer | C14: Semantic layer enabling any user to ask 'why did X' with sourced, narrated answers. | D14: Sales Ops; FP&A; Data/BI | E14: Cost-to-Serve | F14: CIO/CDO / Tech & Data | G14: NL-Analytics | H14: 3.4 | I14: High | J14: Productizable | K14: Phase 3 | L14: Horizontal platform; removes analyst bottleneck firm-wide; strong reuse.
A15: 11 | B15: Collections Copilot + Dynamic Credit | C15: Propensity-to-pay prioritisation, tailored dunning, call summaries; dynamic credit-review memos and limit recommendations. | D15: O2C (Collections/Credit) | E15: Working Capital | F15: CFO / Finance | G15: Copilot / Agent-Assist | H15: 3.6 | I15: High | J15: Productizable | K15: Phase 3 | L15: Compounds the Phase-1 cash gains; relationship-aware automation.
A16: 12 | B16: MDM Spine + HSN Governance | C16: Dedup + GTIN cross-map, UOM/pack normalisation, HSN/tax classification, live anomaly governance. | D16: MDM; Tax; Procurement | E16: Risk / Compliance | F16: CIO/CDO / Tech & Data | G16: Doc-Extraction + Semantic Search | H16: 3.2 | I16: High | J16: Productizable | K16: Phase 3 | L16: The prerequisite that makes everything else reliable; sticky, recurring engagement.
